__init__.py
poetry_to_uv/__init__.py
poetry_to_uv/__main__.py
poetry_to_uv/constants.py
poetry_to_uv/convertor.py
poetry_to_uv/poetry.py
poetry_to_uv/typing.py
poetry_to_uv/validation.py
poetry_to_uv-0.0.4.dist-info/METADATA
poetry_to_uv-0.0.4.dist-info/WHEEL
poetry_to_uv-0.0.4.dist-info/entry_points.txt
poetry_to_uv-0.0.4.dist-info/top_level.txt
poetry_to_uv-0.0.4.dist-info/RECORD
