Metadata-Version: 2.1
Name: poetry-to-uv
Version: 0.0.4
Summary: Help make the migration from using a Poetry pyproject.toml file to a UV compatible pyproject.toml file.
Requires-Python: >=3.7
Requires-Dist: tomlkit
Requires-Dist: pydantic
Requires-Dist: packaging
Provides-Extra: testing
Requires-Dist: pdbpp ; extra == 'testing'
Requires-Dist: ruff ; extra == 'testing'
Requires-Dist: mypy ; extra == 'testing'
